orchestra_client/__init__.py
orchestra_client/cli.py
orchestra_client/connect.py
orchestra_client/launch.py
orchestra_client/maestro.py
orchestra_client/ssh_proxy.py
orchestra_client/upload.py
orchestra_client/frontend/__init__.py
orchestra_client/frontend/app.py
orchestra_client/frontend/state.py
orchestra_client/frontend/widgets/__init__.py
orchestra_client/frontend/widgets/diff_tab.py
orchestra_client/frontend/widgets/hud.py
orchestra_client/frontend/widgets/messages_tab.py
orchestra_client/lib/__init__.py
orchestra_client/lib/config.py
orchestra_client/lib/logger.py
orchestra_client/lib/message.py
orchestra_client/lib/session.py
orchestra_client/lib/helpers/__init__.py
orchestra_client/lib/helpers/file_ops.py
orchestra_client/lib/helpers/process.py
orchestra_client/lib/helpers/tmux.py
orchestra_client-0.1.2.dist-info/METADATA
orchestra_client-0.1.2.dist-info/WHEEL
orchestra_client-0.1.2.dist-info/entry_points.txt
orchestra_client-0.1.2.dist-info/top_level.txt
orchestra_client-0.1.2.dist-info/RECORD
