Metadata-Version: 2.4
Name: orchestra-client
Version: 0.1.2
Summary: Orchestra Client - TUI and CLI tools for managing Claude sessions
Requires-Python: >=3.11
Requires-Dist: textual>=5.3.0
Requires-Dist: websockets>=12.0
Requires-Dist: requests>=2.30.0
Requires-Dist: pyyaml>=6.0
